sapsan/__init__.py
sapsan/_version.py
sapsan/core/__init__.py
sapsan/core/models.py
sapsan/core/abstrctions/__init__.py
sapsan/core/abstrctions/algorithm.py
sapsan/core/abstrctions/dataset.py
sapsan/core/abstrctions/experiment.py
sapsan/core/abstrctions/tracking.py
sapsan/core/cli/__init__.py
sapsan/core/cli/cli.py
sapsan/core/cli/templates/__init__.py
sapsan/core/cli/templates/actions.py
sapsan/core/cli/templates/dataset.py
sapsan/core/cli/templates/docker.py
sapsan/core/cli/templates/estimator.py
sapsan/core/cli/templates/experiment.py
sapsan/core/cli/templates/makefile.py
sapsan/core/cli/templates/notebook.py
sapsan/core/cli/templates/readme.py
sapsan/core/cli/templates/requirements.py
sapsan/core/cli/templates/runner.py
sapsan/core/cli/templates/setup.py
sapsan/core/cli/templates/test.py
sapsan/core/tracking/__init__.py
sapsan/core/tracking/logger.py
sapsan/examples/cnn_example.ipynb
sapsan/examples/krr_example.ipynb
sapsan/examples/picae_example.ipynb
sapsan/examples/pimlturb1d_example.ipynb
sapsan/examples/pimlturb_diagonal_example.ipynb
sapsan/examples/plotting_examples.ipynb
sapsan/examples/GUI/Welcome.py
sapsan/examples/GUI/config.txt
sapsan/examples/GUI/pages/Examples.py
sapsan/examples/data/1dccsn/s12.0.swbj15.horo.3d/dump_00030.h5
sapsan/examples/data/1dccsn/s12.0.swbj15.horo.3d/dump_00035.h5
sapsan/examples/data/1dccsn/s12.0.swbj15.horo.3d/dump_00040.h5
sapsan/examples/data/1dccsn/s12.0.swbj15.horo.3d/dump_00050.h5
sapsan/examples/data/1dccsn/s12.0.swbj15.horo.3d/dump_00060.h5
sapsan/examples/data/1dccsn/s12.0.swbj15.horo.3d/dump_00065.h5
sapsan/examples/data/1dccsn/s12.0.swbj15.horo.3d/dump_00070.h5
sapsan/examples/data/1dccsn/s12.0.swbj15.horo.3d/dump_00080.h5
sapsan/examples/data/1dccsn/s12.0.swbj15.horo.3d/dump_00090.h5
sapsan/examples/data/1dccsn/s12.0.swbj15.horo.3d/dump_00095.h5
sapsan/examples/data/1dccsn/s12.0.swbj15.horo.3d/dump_00100.h5
sapsan/examples/data/1dccsn/s12.0.swbj15.horo.3d/dump_00110.h5
sapsan-0.6.5.dist-info/LICENSE
sapsan-0.6.5.dist-info/METADATA
sapsan-0.6.5.dist-info/WHEEL
sapsan-0.6.5.dist-info/entry_points.txt
sapsan-0.6.5.dist-info/top_level.txt
sapsan-0.6.5.dist-info/RECORD
