Metadata-Version: 2.1
Name: sapsan
Version: 0.6.5
Summary: Sapsan project
Home-page: https://github.com/pikarpov-LANL/Sapsan
Author: Platon Karpov, Iskandar Sitdikov
Author-email: plkarpov@ucsc.edu
License: BSD
Keywords: experiments,reproducibility,astrophysics
Classifier: License :: OSI Approved :: BSD License
Classifier: Programming Language :: Python :: 3
Classifier: Programming Language :: Python :: 3.7
Classifier: Programming Language :: Python :: 3.8
Classifier: Programming Language :: Python :: 3.9
Classifier: Programming Language :: Python :: 3.10
Requires-Python: >=3.7, <3.11
License-File: LICENSE
Requires-Dist: protobuf ==3.20.*
Requires-Dist: catalyst <=21.12,>=21.5
Requires-Dist: Click >=7.1.2
Requires-Dist: graphviz >=0.20
Requires-Dist: h5py >=2.10.0
Requires-Dist: jupyter >=1.0.0
Requires-Dist: jupytext >=1.11
Requires-Dist: matplotlib >=3.3.2
Requires-Dist: mlflow >=1.23
Requires-Dist: notebook >=6.4.3
Requires-Dist: numpy >=v1.21.0
Requires-Dist: opencv-python >=4.5.4
Requires-Dist: pandas >=1.1.0
Requires-Dist: Pillow >=8.1.0
Requires-Dist: plotly >=5.2.0
Requires-Dist: pytest >=6.2
Requires-Dist: safitty >=1.3
Requires-Dist: scikit-image >=0.19.3
Requires-Dist: scikit-learn >=1.0.2
Requires-Dist: scipy >=1.7.3
Requires-Dist: six >=1.15.0
Requires-Dist: streamlit >=1.12.0
Requires-Dist: tornado >=6.1.0
